Metadata-Version: 2.1
Name: ironegg
Version: 1.0.8
Summary: utils strong like ironegg
Home-page: https://github.com/yxzoro/ironegg
Author: xingyang
Author-email: xing.yang@intel.com
License: MIT License
Platform: UNKNOWN
Classifier: Intended Audience :: Developers
Classifier: Operating System :: OS Independent
Classifier: Programming Language :: Python :: 2
Classifier: Programming Language :: Python :: 3
Classifier: Topic :: Software Development :: Libraries
